self_serve_platform/__init__.py
self_serve_platform/agents/__init__.py
self_serve_platform/agents/reasoning_engine.py
self_serve_platform/agents/reasoning_engines/__init__.py
self_serve_platform/agents/reasoning_engines/base.py
self_serve_platform/agents/reasoning_engines/langchain_for_openai.py
self_serve_platform/agents/reasoning_engines/llamaindex_react.py
self_serve_platform/agents/task_force.py
self_serve_platform/agents/task_forces/__init__.py
self_serve_platform/agents/task_forces/base.py
self_serve_platform/agents/task_forces/crewai_multi_agent.py
self_serve_platform/agents/task_forces/langgraph_multi_agent.py
self_serve_platform/agents/tool_repositories/__init__.py
self_serve_platform/agents/tool_repositories/base.py
self_serve_platform/agents/tool_repositories/langchain_structured.py
self_serve_platform/agents/tool_repository.py
self_serve_platform/chat/__init__.py
self_serve_platform/chat/memories/__init__.py
self_serve_platform/chat/memories/base.py
self_serve_platform/chat/memories/langchain_buffer.py
self_serve_platform/chat/memories/langchain_buffer_window.py
self_serve_platform/chat/memories/langchain_chroma_store_retriever.py
self_serve_platform/chat/memories/langchain_remote_memory.py
self_serve_platform/chat/memories/langchain_summary.py
self_serve_platform/chat/memories/llamaindex_buffer.py
self_serve_platform/chat/memory.py
self_serve_platform/chat/message_manager.py
self_serve_platform/chat/message_managers/__init__.py
self_serve_platform/chat/message_managers/base.py
self_serve_platform/chat/message_managers/langchain_prompts.py
self_serve_platform/chat/model.py
self_serve_platform/chat/models/__init__.py
self_serve_platform/chat/models/base.py
self_serve_platform/chat/models/langchain_azure_chat_openai.py
self_serve_platform/chat/models/langchain_chat_anthropic.py
self_serve_platform/chat/models/langchain_chat_google_genai.py
self_serve_platform/chat/models/langchain_chat_mistralai.py
self_serve_platform/chat/models/langchain_chat_nvidia.py
llmesh-0.1.4.dist-info/LICENCE.md
llmesh-0.1.4.dist-info/METADATA
llmesh-0.1.4.dist-info/WHEEL
llmesh-0.1.4.dist-info/RECORD
