Metadata-Version: 2.1
Name: llmesh
Version: 0.1.4
Summary: HPE LLM Agentic Tool Mesh Platform is an innovative platform designed to streamline and enhance the use of AI in various applications. It serves as a central hub to orchestrate 'Intelligent Plugins,' optimizing AI interactions and processes.
Home-page: https://github.com/HewlettPackard/llmesh/wiki
License: MIT
Keywords: HPE,Athon,LLM Agentic Tool Mesh,LLM Agentic Tool Platform
Author: Antonio Fin
Author-email: antonio.fin@hpe.com
Requires-Python: >=3.11,<3.13
Classifier: Development Status :: 4 - Beta
Classifier: Intended Audience :: Developers
Classifier: License :: OSI Approved :: MIT License
Classifier: Programming Language :: Python :: 3
Classifier: Programming Language :: Python :: 3.11
Classifier: Programming Language :: Python :: 3.12
Provides-Extra: agents
Provides-Extra: all
Provides-Extra: chat
Provides-Extra: rag
Provides-Extra: test
Requires-Dist: PyMuPDF (>=1.24.11,<2.0.0) ; extra == "rag" or extra == "all"
Requires-Dist: chromadb (>0.4.24,<0.6.00) ; extra == "rag" or extra == "all"
Requires-Dist: crewai[tools] (>0.80.0,<0.90.0) ; extra == "agents" or extra == "all"
Requires-Dist: flask (>=3.0.3,<4.0.0)
Requires-Dist: jinja2 (>=3.1.4,<4.0.0)
Requires-Dist: langchain (>=0.3.4,<0.4.0)
Requires-Dist: langchain-anthropic (>=0.2.3,<0.3.0) ; extra == "chat" or extra == "agents" or extra == "rag" or extra == "all"
Requires-Dist: langchain-community (>=0.3.3,<0.4.0) ; extra == "chat" or extra == "agents" or extra == "rag" or extra == "all"
Requires-Dist: langchain-google-genai (>=2.0.1,<3.0.0) ; extra == "chat" or extra == "agents" or extra == "rag" or extra == "all"
Requires-Dist: langchain-mistralai (>=0.2.0,<0.3.0) ; extra == "chat" or extra == "agents" or extra == "rag" or extra == "all"
Requires-Dist: langchain-nvidia-ai-endpoints (>=0.3.0,<0.4.0) ; extra == "chat" or extra == "agents" or extra == "rag" or extra == "all"
Requires-Dist: langchain-openai (>=0.2.3,<0.3.0) ; extra == "chat" or extra == "agents" or extra == "rag" or extra == "all"
Requires-Dist: langgraph (>=0.2.39,<0.3.0) ; extra == "agents" or extra == "all"
Requires-Dist: llama-index (>=0.11,<0.12) ; extra == "chat" or extra == "agents" or extra == "rag" or extra == "all"
Requires-Dist: llama-index-llms-openai (>=0.2,<0.3) ; extra == "chat" or extra == "agents" or extra == "rag" or extra == "all"
Requires-Dist: markitdown (>=0.0.1a3,<0.1.0) ; extra == "rag" or extra == "all"
Requires-Dist: matplotlib (>=3.9.2,<4.0.0) ; extra == "rag" or extra == "all"
Requires-Dist: openpyxl (>=3.1.5,<4.0.0) ; extra == "rag" or extra == "all"
Requires-Dist: pydantic (>=2.9.2,<3.0.0)
Requires-Dist: pymilvus[model] (>=2.5.3,<3.0.0) ; extra == "rag" or extra == "all"
Requires-Dist: pyopenssl (>=24.2.1,<25.0.0)
Requires-Dist: pytest (>=8.3.3,<9.0.0) ; extra == "test"
Requires-Dist: pytest-optional-tests (>=0.1.1,<0.2.0) ; extra == "test"
Requires-Dist: python-certifi-win32 (>=1.6.1,<2.0.0) ; sys_platform == "win32"
Requires-Dist: python-multipart (>=0.0.18,<0.0.21)
Requires-Dist: pyyaml (>=6.0.2,<7.0.0)
Requires-Dist: qdrant-client (>1.12.0,<1.13.0) ; extra == "rag" or extra == "all"
Requires-Dist: sentence-transformers (>3.2.0,<3.4.0) ; extra == "rag" or extra == "all"
Requires-Dist: transformers (>=4.48.0) ; extra == "rag" or extra == "all"
Requires-Dist: umap (>=0.1.1,<0.2.0) ; extra == "rag" or extra == "all"
Requires-Dist: umap-learn (>=0.5.7,<0.6.0) ; extra == "rag" or extra == "all"
Requires-Dist: unstructured[docx,pdf,pptx,xlsx] (>=0.16.0,<0.17.0) ; extra == "rag" or extra == "all"
Requires-Dist: vllm (>=0.7.3,<0.8.0) ; extra == "chat" or extra == "agents" or extra == "rag" or extra == "all"
Project-URL: Repository, https://github.com/HewlettPackard/llmesh
